[[{"id":12977,"icon":2,"nameId":797946,"descriptionId":929129,"spellLevels":[41030,41031,41032]},{"id":13008,"icon":3772,"nameId":797872,"descriptionId":929131,"spellLevels":[41121,44047]},{"id":12978,"icon":3,"nameId":797820,"descriptionId":929136,"spellLevels":[41033,41034,41035]},{"id":13007,"icon":3773,"nameId":797818,"descriptionId":902381,"spellLevels":[41120,44046]},{"id":12981,"icon":6,"nameId":797911,"descriptionId":929297,"spellLevels":[41042,41043,41044]},{"id":13009,"icon":3771,"nameId":797896,"descriptionId":929135,"spellLevels":[41122,44045]},{"id":12976,"icon":1,"nameId":797901,"descriptionId":929137,"spellLevels":[41027,41028,41029]},{"id":13010,"icon":3770,"nameId":797821,"descriptionId":929138,"spellLevels":[41123,44048]},{"id":12994,"icon":19,"nameId":797862,"descriptionId":966665,"spellLevels":[41081,41082,41083]},{"id":13011,"icon":3776,"nameId":797863,"descriptionId":903556,"spellLevels":[41124,44049]},{"id":12979,"icon":4,"nameId":797832,"descriptionId":932839,"spellLevels":[41036,41037,41038]},{"id":13016,"icon":3775,"nameId":797910,"descriptionId":929190,"spellLevels":[41129,44050]},{"id":12992,"icon":17,"nameId":797925,"descriptionId":929207,"spellLevels":[41075,41076,41077]},{"id":13013,"icon":3778,"nameId":797912,"descriptionId":938955,"spellLevels":[41126,44051]},{"id":12993,"icon":18,"nameId":797952,"descriptionId":929144,"spellLevels":[41078,41079,41080]},{"id":13014,"icon":3777,"nameId":797826,"descriptionId":929145,"spellLevels":[41127,44057]},{"id":12984,"icon":9,"nameId":797844,"descriptionId":929146,"spellLevels":[41051,41052,41053]},{"id":13015,"icon":3786,"nameId":797816,"descriptionId":929205,"spellLevels":[41128]},{"id":12995,"icon":20,"nameId":797922,"descriptionId":932837,"spellLevels":[41084,41085,41086]},{"id":13012,"icon":3769,"nameId":942863,"descriptionId":797810,"spellLevels":[41125]},{"id":12983,"icon":8,"nameId":921278,"descriptionId":929150,"spellLevels":[41048,41049,41050]},{"id":13017,"icon":3787,"nameId":797921,"descriptionId":797838,"spellLevels":[41130]},{"id":12986,"icon":11,"nameId":797941,"descriptionId":929181,"spellLevels":[41057,41058,41059]},{"id":13018,"icon":3784,"nameId":797870,"descriptionId":929192,"spellLevels":[41131]},{"id":12988,"icon":13,"nameId":797822,"descriptionId":929189,"spellLevels":[41063,41064,41065]},{"id":13019,"icon":3782,"nameId":797854,"descriptionId":929193,"spellLevels":[41132]},{"id":12980,"icon":5,"nameId":797948,"descriptionId":979766,"spellLevels":[41039,41040,41041]},{"id":13020,"icon":10434,"nameId":797886,"descriptionId":929185,"spellLevels":[41133]},{"id":12987,"icon":12,"nameId":797813,"descriptionId":929206,"spellLevels":[41060,41061,41062]},{"id":13021,"icon":3783,"nameId":797939,"descriptionId":938954,"spellLevels":[41134]},{"id":12989,"icon":14,"nameId":797873,"descriptionId":929210,"spellLevels":[41066,41067,41068]},{"id":13022,"icon":3781,"nameId":797913,"descriptionId":929211,"spellLevels":[41135]},{"id":12990,"icon":15,"nameId":797817,"descriptionId":936531,"spellLevels":[41069,41070,41071]},{"id":13023,"icon":3780,"nameId":797858,"descriptionId":938956,"spellLevels":[41136]},{"id":12997,"icon":422,"nameId":797879,"descriptionId":942930,"spellLevels":[41090,41091]},{"id":13027,"icon":3774,"nameId":797819,"descriptionId":939227,"spellLevels":[41140]},{"id":12991,"icon":16,"nameId":929217,"descriptionId":929218,"spellLevels":[41072,41073]},{"id":13024,"icon":3779,"nameId":797852,"descriptionId":929219,"spellLevels":[41137]},{"id":12985,"icon":10,"nameId":797897,"descriptionId":929221,"spellLevels":[41054,41055]},{"id":13025,"icon":3785,"nameId":797918,"descriptionId":938943,"spellLevels":[41138]},{"id":14434,"icon":4055,"nameId":805260,"descriptionId":929214,"spellLevels":[44058,44060]},{"id":14436,"icon":4056,"nameId":805272,"descriptionId":929459,"spellLevels":[44065]},{"id":12982,"icon":7,"nameId":797855,"descriptionId":929292,"spellLevels":[41045,41046]},{"id":13026,"icon":10186,"nameId":797839,"descriptionId":929226,"spellLevels":[41139]}],[{"id":13998,"icon":3971,"nameId":800969,"descriptionId":978395,"spellLevels":[43063,43099,43100]},{"id":12618,"icon":3698,"nameId":796877,"descriptionId":805846,"spellLevels":[40372,43724]},{"id":12548,"icon":21,"nameId":796783,"descriptionId":917933,"spellLevels":[40245,43172,43173]},{"id":14021,"icon":4020,"nameId":800754,"descriptionId":923581,"spellLevels":[43110,43181]},{"id":12615,"icon":3693,"nameId":796832,"descriptionId":978919,"spellLevels":[40369,40400,40401]},{"id":14017,"icon":4021,"nameId":800614,"descriptionId":976802,"spellLevels":[43106,43183]},{"id":12549,"icon":22,"nameId":796825,"descriptionId":978918,"spellLevels":[40248,40249,40250]},{"id":12600,"icon":3704,"nameId":796850,"descriptionId":927898,"spellLevels":[40354,43493]},{"id":12555,"icon":4022,"nameId":796852,"descriptionId":978917,"spellLevels":[40262,40263,40264]},{"id":12604,"icon":3697,"nameId":796820,"descriptionId":918731,"spellLevels":[40358,43196]},{"id":12606,"icon":3689,"nameId":796931,"descriptionId":979366,"spellLevels":[40360,43197,43198]},{"id":14008,"icon":3968,"nameId":800963,"descriptionId":978398,"spellLevels":[43084,43085]},{"id":12557,"icon":30,"nameId":796889,"descriptionId":924382,"spellLevels":[40268,43202]},{"id":12608,"icon":3695,"nameId":796762,"descriptionId":965739,"spellLevels":[40362]},{"id":12601,"icon":3705,"nameId":796930,"descriptionId":978916,"spellLevels":[40355,43210,43211]},{"id":14018,"icon":4025,"nameId":801228,"descriptionId":918770,"spellLevels":[43107,43216]},{"id":14022,"icon":4026,"nameId":800819,"descriptionId":925271,"spellLevels":[43111,43223,43224]},{"id":14023,"icon":4027,"nameId":800827,"descriptionId":978414,"spellLevels":[43112]},{"id":12560,"icon":33,"nameId":796933,"descriptionId":978920,"spellLevels":[40275,43231,43232]},{"id":12609,"icon":3692,"nameId":796817,"descriptionId":918995,"spellLevels":[40363]},{"id":14006,"icon":3966,"nameId":800967,"descriptionId":978394,"spellLevels":[43077,43078,43079]},{"id":12559,"icon":32,"nameId":919749,"descriptionId":918750,"spellLevels":[40274]},{"id":12563,"icon":36,"nameId":918005,"descriptionId":918006,"spellLevels":[40284,43246,43247]},{"id":12614,"icon":3690,"nameId":796873,"descriptionId":919291,"spellLevels":[40368]},{"id":14028,"icon":3699,"nameId":800957,"descriptionId":925836,"spellLevels":[43117,43306,54417]},{"id":12619,"icon":4028,"nameId":796809,"descriptionId":806357,"spellLevels":[40373]},{"id":12554,"icon":27,"nameId":805859,"descriptionId":983728,"spellLevels":[40259,40260,40261]},{"id":14009,"icon":3969,"nameId":800961,"descriptionId":978397,"spellLevels":[43086]},{"id":12551,"icon":24,"nameId":903505,"descriptionId":978921,"spellLevels":[40252,44522,44523]},{"id":12612,"icon":3702,"nameId":801515,"descriptionId":966694,"spellLevels":[40366]},{"id":14019,"icon":4029,"nameId":800854,"descriptionId":978923,"spellLevels":[43108,43255,43256]},{"id":14020,"icon":4276,"nameId":801231,"descriptionId":978413,"spellLevels":[43109]},{"id":12550,"icon":23,"nameId":796768,"descriptionId":937904,"spellLevels":[40251,43463,43464]},{"id":14015,"icon":4031,"nameId":800901,"descriptionId":924211,"spellLevels":[43104]},{"id":12605,"icon":3700,"nameId":796955,"descriptionId":966691,"spellLevels":[40359,43278]},{"id":14016,"icon":4032,"nameId":801240,"descriptionId":966695,"spellLevels":[43105]},{"id":18535,"icon":4271,"nameId":871884,"descriptionId":979768,"spellLevels":[50983,50984]},{"id":18656,"icon":4272,"nameId":871885,"descriptionId":978185,"spellLevels":[51254]},{"id":14026,"icon":4024,"nameId":801276,"descriptionId":925838,"spellLevels":[43115,43516,55261]},{"id":14025,"icon":4023,"nameId":801268,"descriptionId":965917,"spellLevels":[43114,55271]},{"id":14007,"icon":3967,"nameId":800965,"descriptionId":978393,"spellLevels":[43081,43082]},{"id":12617,"icon":3694,"nameId":796775,"descriptionId":922134,"spellLevels":[40371]},{"id":12564,"icon":37,"nameId":796860,"descriptionId":922094,"spellLevels":[40287,43249]},{"id":14010,"icon":3970,"nameId":800959,"descriptionId":978396,"spellLevels":[43091]}],[{"id":13338,"icon":51,"nameId":798557,"descriptionId":936728,"spellLevels":[41718,41719,41720]},{"id":13363,"icon":3809,"nameId":936263,"descriptionId":969874,"spellLevels":[41769,43684]},{"id":13336,"icon":49,"nameId":798562,"descriptionId":936785,"spellLevels":[41712,41713,41714]},{"id":13367,"icon":3801,"nameId":936289,"descriptionId":966646,"spellLevels":[41773]},{"id":13328,"icon":41,"nameId":798604,"descriptionId":966649,"spellLevels":[41688,41689,41690]},{"id":13354,"icon":3793,"nameId":798602,"descriptionId":966652,"spellLevels":[41760,43682]},{"id":13331,"icon":44,"nameId":798649,"descriptionId":936748,"spellLevels":[41697,41698,41699]},{"id":14273,"icon":4035,"nameId":936267,"descriptionId":936268,"spellLevels":[43673,43674]},{"id":14278,"icon":4034,"nameId":937919,"descriptionId":936329,"spellLevels":[43698,43699,43700]},{"id":13360,"icon":3803,"nameId":798626,"descriptionId":936331,"spellLevels":[41766]},{"id":13342,"icon":55,"nameId":798618,"descriptionId":888261,"spellLevels":[41730,41731,41732]},{"id":13356,"icon":3791,"nameId":798580,"descriptionId":936751,"spellLevels":[41762,43686]},{"id":13334,"icon":47,"nameId":798610,"descriptionId":936752,"spellLevels":[41706,41707,41708]},{"id":13357,"icon":3790,"nameId":798628,"descriptionId":967924,"spellLevels":[41763,43687]},{"id":13340,"icon":53,"nameId":798631,"descriptionId":936754,"spellLevels":[41724,41725,41726]},{"id":13352,"icon":10909,"nameId":936305,"descriptionId":969875,"spellLevels":[41758,43681]},{"id":13332,"icon":45,"nameId":936758,"descriptionId":936756,"spellLevels":[41700,41701,41702]},{"id":13359,"icon":3808,"nameId":936757,"descriptionId":936279,"spellLevels":[41765]},{"id":13364,"icon":3805,"nameId":798655,"descriptionId":936998,"spellLevels":[41770,56936,56937]},{"id":13372,"icon":3796,"nameId":798630,"descriptionId":936790,"spellLevels":[41778]},{"id":13344,"icon":57,"nameId":798616,"descriptionId":966648,"spellLevels":[41736,41737,41738]},{"id":13361,"icon":3800,"nameId":798620,"descriptionId":966651,"spellLevels":[41767]},{"id":13339,"icon":52,"nameId":798658,"descriptionId":936782,"spellLevels":[41721,41722,41723]},{"id":13362,"icon":3804,"nameId":798584,"descriptionId":941273,"spellLevels":[41768]},{"id":13365,"icon":3802,"nameId":798575,"descriptionId":798558,"spellLevels":[41771,43685,60038]},{"id":13358,"icon":3806,"nameId":798661,"descriptionId":960544,"spellLevels":[41764]},{"id":13337,"icon":50,"nameId":798627,"descriptionId":798560,"spellLevels":[41715,41716,41717]},{"id":13329,"icon":42,"nameId":936297,"descriptionId":936787,"spellLevels":[41691]},{"id":13335,"icon":48,"nameId":798656,"descriptionId":958810,"spellLevels":[41709,41710,41711]},{"id":13355,"icon":3792,"nameId":936275,"descriptionId":936755,"spellLevels":[41761,56924]},{"id":13366,"icon":3810,"nameId":798569,"descriptionId":936749,"spellLevels":[41772,43689,43690]},{"id":13353,"icon":3794,"nameId":798551,"descriptionId":969876,"spellLevels":[41759,60044]},{"id":13343,"icon":56,"nameId":936280,"descriptionId":798568,"spellLevels":[41733,41734,41735]},{"id":13330,"icon":43,"nameId":798587,"descriptionId":961378,"spellLevels":[41694]},{"id":13349,"icon":425,"nameId":802327,"descriptionId":936799,"spellLevels":[41751,41752]},{"id":14274,"icon":4036,"nameId":937129,"descriptionId":959963,"spellLevels":[43676]},{"id":13346,"icon":59,"nameId":798543,"descriptionId":937011,"spellLevels":[41742,41743]},{"id":13369,"icon":3798,"nameId":798549,"descriptionId":958142,"spellLevels":[41775]},{"id":13333,"icon":46,"nameId":798565,"descriptionId":936916,"spellLevels":[41703,41704]},{"id":13368,"icon":3799,"nameId":936343,"descriptionId":976498,"spellLevels":[41774]},{"id":13345,"icon":58,"nameId":936368,"descriptionId":936791,"spellLevels":[41739,41740]},{"id":13370,"icon":10427,"nameId":936369,"descriptionId":936796,"spellLevels":[41776]},{"id":13347,"icon":60,"nameId":798619,"descriptionId":966647,"spellLevels":[41745,41746]},{"id":13371,"icon":3797,"nameId":936823,"descriptionId":966650,"spellLevels":[41777]}],[{"id":12913,"icon":72,"nameId":797777,"descriptionId":963263,"spellLevels":[40916,40917,40918]},{"id":12930,"icon":3631,"nameId":797770,"descriptionId":963262,"spellLevels":[40967,43791]},{"id":12906,"icon":65,"nameId":797659,"descriptionId":966622,"spellLevels":[40895,40896,40897]},{"id":12935,"icon":3640,"nameId":933359,"descriptionId":966637,"spellLevels":[40972,43794]},{"id":12902,"icon":61,"nameId":807239,"descriptionId":797775,"spellLevels":[40883,40884,40885]},{"id":12932,"icon":3642,"nameId":933357,"descriptionId":930914,"spellLevels":[40969,43788]},{"id":12907,"icon":66,"nameId":930495,"descriptionId":930541,"spellLevels":[40898,40899,40900]},{"id":12933,"icon":3637,"nameId":797710,"descriptionId":966255,"spellLevels":[40970,43792]},{"id":12914,"icon":73,"nameId":807238,"descriptionId":930734,"spellLevels":[40919,40920,40921]},{"id":12922,"icon":416,"nameId":797771,"descriptionId":931283,"spellLevels":[40943]},{"id":12904,"icon":63,"nameId":797658,"descriptionId":930554,"spellLevels":[40889,40890,40891]},{"id":12939,"icon":3625,"nameId":933360,"descriptionId":931285,"spellLevels":[40976,52961]},{"id":12915,"icon":74,"nameId":797739,"descriptionId":930670,"spellLevels":[40922,40923,40924]},{"id":12936,"icon":3629,"nameId":797801,"descriptionId":930921,"spellLevels":[40973,43796]},{"id":12916,"icon":75,"nameId":797707,"descriptionId":966623,"spellLevels":[40925,40926,40927]},{"id":12937,"icon":4037,"nameId":797795,"descriptionId":930923,"spellLevels":[40974,43797]},{"id":12920,"icon":79,"nameId":797768,"descriptionId":966624,"spellLevels":[40937,40938,40939]},{"id":12938,"icon":3624,"nameId":807245,"descriptionId":807402,"spellLevels":[40975]},{"id":12919,"icon":78,"nameId":797780,"descriptionId":930719,"spellLevels":[40934,40935,40936]},{"id":12942,"icon":3634,"nameId":797687,"descriptionId":966636,"spellLevels":[40979]},{"id":12948,"icon":3627,"nameId":797731,"descriptionId":966628,"spellLevels":[40985,44724,44725]},{"id":12943,"icon":3626,"nameId":797735,"descriptionId":979576,"spellLevels":[40980]},{"id":12910,"icon":69,"nameId":797665,"descriptionId":896558,"spellLevels":[40907,40908,40909]},{"id":14314,"icon":4038,"nameId":803133,"descriptionId":966634,"spellLevels":[43798]},{"id":12909,"icon":68,"nameId":797776,"descriptionId":931448,"spellLevels":[40904,40905,40906]},{"id":12940,"icon":3632,"nameId":797682,"descriptionId":966630,"spellLevels":[40977]},{"id":12918,"icon":77,"nameId":797750,"descriptionId":930553,"spellLevels":[40931,40932,40933]},{"id":12911,"icon":70,"nameId":797666,"descriptionId":807401,"spellLevels":[40910,40911]},{"id":12908,"icon":67,"nameId":797792,"descriptionId":930735,"spellLevels":[40901,40902,40903]},{"id":12945,"icon":3636,"nameId":797760,"descriptionId":966258,"spellLevels":[40982]},{"id":12903,"icon":62,"nameId":797752,"descriptionId":966254,"spellLevels":[40886,40887,40888]},{"id":14741,"icon":4121,"nameId":807260,"descriptionId":894694,"spellLevels":[44739]},{"id":12917,"icon":76,"nameId":797753,"descriptionId":930855,"spellLevels":[40928,40930]},{"id":14742,"icon":4122,"nameId":807271,"descriptionId":931288,"spellLevels":[44741]},{"id":14312,"icon":444,"nameId":803128,"descriptionId":966250,"spellLevels":[43790,43799]},{"id":14313,"icon":4040,"nameId":803130,"descriptionId":966259,"spellLevels":[43795]},{"id":12941,"icon":3641,"nameId":797721,"descriptionId":966627,"spellLevels":[40978,44731,44732]},{"id":12905,"icon":64,"nameId":797762,"descriptionId":930962,"spellLevels":[40892]},{"id":12934,"icon":3635,"nameId":797660,"descriptionId":966626,"spellLevels":[40971,43793]},{"id":12950,"icon":3622,"nameId":797767,"descriptionId":966633,"spellLevels":[40987]},{"id":12921,"icon":80,"nameId":797677,"descriptionId":930853,"spellLevels":[40940,40942]},{"id":12949,"icon":3623,"nameId":797781,"descriptionId":931290,"spellLevels":[40986]},{"id":12931,"icon":3638,"nameId":807268,"descriptionId":966625,"spellLevels":[40968,43789]},{"id":12947,"icon":4039,"nameId":797740,"descriptionId":966632,"spellLevels":[40984]}],[{"id":13249,"icon":88,"nameId":798424,"descriptionId":975832,"spellLevels":[41547,41548,41549]},{"id":13282,"icon":3719,"nameId":798513,"descriptionId":976419,"spellLevels":[41629,44509]},{"id":13244,"icon":83,"nameId":798536,"descriptionId":976196,"spellLevels":[41532,41533,41534]},{"id":13283,"icon":3724,"nameId":798486,"descriptionId":976470,"spellLevels":[41630,44508]},{"id":13242,"icon":81,"nameId":798447,"descriptionId":977145,"spellLevels":[41526,41527,41528]},{"id":13281,"icon":3726,"nameId":798525,"descriptionId":976409,"spellLevels":[41628,44507]},{"id":13254,"icon":93,"nameId":798387,"descriptionId":976215,"spellLevels":[41562,41563,41564]},{"id":13284,"icon":3714,"nameId":798452,"descriptionId":976414,"spellLevels":[41631,44510]},{"id":13243,"icon":3713,"nameId":798379,"descriptionId":981341,"spellLevels":[41529,41530,41531]},{"id":13285,"icon":4344,"nameId":798528,"descriptionId":976416,"spellLevels":[41632,44511]},{"id":13253,"icon":92,"nameId":798371,"descriptionId":976374,"spellLevels":[41559,41561]},{"id":13286,"icon":3715,"nameId":798512,"descriptionId":976465,"spellLevels":[41633]},{"id":13287,"icon":3710,"nameId":798444,"descriptionId":980092,"spellLevels":[41634,41680,41681]},{"id":13258,"icon":97,"nameId":798365,"descriptionId":976421,"spellLevels":[41574,44513]},{"id":13245,"icon":84,"nameId":798494,"descriptionId":976237,"spellLevels":[41535,41536,41537]},{"id":13288,"icon":3723,"nameId":798416,"descriptionId":976422,"spellLevels":[41635,44514]},{"id":13261,"icon":100,"nameId":798472,"descriptionId":976259,"spellLevels":[41581,41582,41583]},{"id":13289,"icon":3707,"nameId":798496,"descriptionId":976433,"spellLevels":[41636]},{"id":13259,"icon":98,"nameId":798376,"descriptionId":976260,"spellLevels":[41575,41576,41577]},{"id":13290,"icon":3709,"nameId":798394,"descriptionId":976491,"spellLevels":[41637]},{"id":13246,"icon":10617,"nameId":798397,"descriptionId":976264,"spellLevels":[41538,41539,41540]},{"id":13291,"icon":10734,"nameId":798389,"descriptionId":976460,"spellLevels":[41638]},{"id":13257,"icon":96,"nameId":798522,"descriptionId":976291,"spellLevels":[41571,41572,41573]},{"id":13292,"icon":3711,"nameId":798510,"descriptionId":976461,"spellLevels":[41639]},{"id":13251,"icon":90,"nameId":798368,"descriptionId":983099,"spellLevels":[41553,41555]},{"id":13293,"icon":3717,"nameId":798485,"descriptionId":976472,"spellLevels":[41640]},{"id":13248,"icon":87,"nameId":798476,"descriptionId":976302,"spellLevels":[41544,41545,41546]},{"id":13294,"icon":3720,"nameId":798403,"descriptionId":976463,"spellLevels":[41641]},{"id":13250,"icon":89,"nameId":798391,"descriptionId":976317,"spellLevels":[41550,41551,41552]},{"id":13295,"icon":3718,"nameId":798382,"descriptionId":976480,"spellLevels":[41642]},{"id":13247,"icon":86,"nameId":798520,"descriptionId":976616,"spellLevels":[41541,41542,41543]},{"id":14650,"icon":4059,"nameId":897173,"descriptionId":976477,"spellLevels":[44504]},{"id":13255,"icon":10618,"nameId":798487,"descriptionId":976336,"spellLevels":[41565,41566,41567]},{"id":13297,"icon":4346,"nameId":798500,"descriptionId":982489,"spellLevels":[41644]},{"id":13256,"icon":95,"nameId":798427,"descriptionId":976361,"spellLevels":[41568,41570]},{"id":13298,"icon":3712,"nameId":798458,"descriptionId":976490,"spellLevels":[41645]},{"id":13252,"icon":91,"nameId":798439,"descriptionId":976223,"spellLevels":[41556,41557,41558]},{"id":13299,"icon":3716,"nameId":798431,"descriptionId":976418,"spellLevels":[41646,44512]},{"id":13260,"icon":99,"nameId":798432,"descriptionId":976378,"spellLevels":[41578,41580]},{"id":14651,"icon":4060,"nameId":805757,"descriptionId":976468,"spellLevels":[44505]},{"id":13262,"icon":10751,"nameId":798386,"descriptionId":976301,"spellLevels":[41584,41585,41586]},{"id":13301,"icon":4345,"nameId":798384,"descriptionId":976462,"spellLevels":[41648]},{"id":13296,"icon":3721,"nameId":798508,"descriptionId":976380,"spellLevels":[41643,44506]},{"id":13300,"icon":3708,"nameId":798483,"descriptionId":976488,"spellLevels":[41647]}],[{"id":12842,"icon":103,"nameId":797642,"descriptionId":966471,"spellLevels":[40764,40765,40766]},{"id":12863,"icon":3858,"nameId":797629,"descriptionId":928784,"spellLevels":[40830,43778]},{"id":12848,"icon":109,"nameId":797624,"descriptionId":931432,"spellLevels":[40782,40783,40784]},{"id":12864,"icon":3857,"nameId":797609,"descriptionId":928902,"spellLevels":[40831,43779]},{"id":12841,"icon":102,"nameId":797622,"descriptionId":931866,"spellLevels":[40758,40759,40760]},{"id":12866,"icon":3855,"nameId":797625,"descriptionId":931350,"spellLevels":[40833,43776]},{"id":14310,"icon":4045,"nameId":802991,"descriptionId":803031,"spellLevels":[43772,43773,43774]},{"id":14311,"icon":4046,"nameId":803013,"descriptionId":931429,"spellLevels":[43775,43777]},{"id":12844,"icon":105,"nameId":797636,"descriptionId":931867,"spellLevels":[40770,40771,40772]},{"id":12865,"icon":3856,"nameId":797539,"descriptionId":928786,"spellLevels":[40832,43780]},{"id":12840,"icon":101,"nameId":797598,"descriptionId":928794,"spellLevels":[40761,40762,40763]},{"id":12871,"icon":10183,"nameId":797614,"descriptionId":931885,"spellLevels":[40838]},{"id":12856,"icon":117,"nameId":797591,"descriptionId":928788,"spellLevels":[40806,40807,40808]},{"id":12869,"icon":3863,"nameId":797599,"descriptionId":873115,"spellLevels":[40836,43782]},{"id":12852,"icon":113,"nameId":797621,"descriptionId":928918,"spellLevels":[40794,40795,40796]},{"id":12867,"icon":3854,"nameId":797606,"descriptionId":928792,"spellLevels":[40834,43784]},{"id":12858,"icon":119,"nameId":797628,"descriptionId":966472,"spellLevels":[40812,40813,40814]},{"id":12870,"icon":3861,"nameId":797646,"descriptionId":938168,"spellLevels":[40837]},{"id":12846,"icon":107,"nameId":797608,"descriptionId":797534,"spellLevels":[40776,40777,40778]},{"id":12872,"icon":3870,"nameId":803011,"descriptionId":928787,"spellLevels":[40839,43781]},{"id":12850,"icon":111,"nameId":797560,"descriptionId":966245,"spellLevels":[40788,40789,40790]},{"id":12868,"icon":3853,"nameId":797528,"descriptionId":931433,"spellLevels":[40835]},{"id":12855,"icon":116,"nameId":797568,"descriptionId":966474,"spellLevels":[40803,40804,40805]},{"id":12873,"icon":3864,"nameId":797527,"descriptionId":979354,"spellLevels":[40840]},{"id":12845,"icon":106,"nameId":797619,"descriptionId":932762,"spellLevels":[40773,40774,40775]},{"id":12874,"icon":3871,"nameId":797643,"descriptionId":966544,"spellLevels":[40841]},{"id":12847,"icon":108,"nameId":797601,"descriptionId":928823,"spellLevels":[40779,40780,40781]},{"id":12875,"icon":3869,"nameId":797553,"descriptionId":904072,"spellLevels":[40842]},{"id":12843,"icon":104,"nameId":797638,"descriptionId":979360,"spellLevels":[40767,43786,43787]},{"id":12876,"icon":3872,"nameId":797543,"descriptionId":969878,"spellLevels":[40843]},{"id":12854,"icon":4033,"nameId":797555,"descriptionId":982617,"spellLevels":[40800,40801,40802]},{"id":12877,"icon":3865,"nameId":797605,"descriptionId":928891,"spellLevels":[40844]},{"id":12857,"icon":118,"nameId":797581,"descriptionId":931434,"spellLevels":[40809,40810,40811]},{"id":12878,"icon":3862,"nameId":797654,"descriptionId":928829,"spellLevels":[40845]},{"id":12861,"icon":412,"nameId":797603,"descriptionId":903081,"spellLevels":[40821,40822]},{"id":12883,"icon":3859,"nameId":797630,"descriptionId":928855,"spellLevels":[40850]},{"id":12851,"icon":112,"nameId":797565,"descriptionId":928856,"spellLevels":[40791,40792]},{"id":12880,"icon":3867,"nameId":797617,"descriptionId":930720,"spellLevels":[40847]},{"id":12853,"icon":114,"nameId":797532,"descriptionId":979351,"spellLevels":[40797,40798]},{"id":12881,"icon":3866,"nameId":797567,"descriptionId":928878,"spellLevels":[40848]},{"id":12849,"icon":110,"nameId":797631,"descriptionId":928852,"spellLevels":[40785,40786]},{"id":12879,"icon":3868,"nameId":797623,"descriptionId":980030,"spellLevels":[40846]},{"id":12859,"icon":120,"nameId":797583,"descriptionId":928879,"spellLevels":[40815,40816]},{"id":12882,"icon":3860,"nameId":805210,"descriptionId":928890,"spellLevels":[40849]}],[{"id":13169,"icon":122,"nameId":798229,"descriptionId":979892,"spellLevels":[41386,41387,41388]},{"id":13202,"icon":3813,"nameId":798307,"descriptionId":798326,"spellLevels":[41480,44077]},{"id":13176,"icon":129,"nameId":798214,"descriptionId":979860,"spellLevels":[41407,41408,41409]},{"id":13200,"icon":3815,"nameId":798356,"descriptionId":979861,"spellLevels":[41477,44076]},{"id":13171,"icon":124,"nameId":798217,"descriptionId":979793,"spellLevels":[41392,41393,41394]},{"id":13201,"icon":3814,"nameId":798298,"descriptionId":979831,"spellLevels":[41479,44070]},{"id":13172,"icon":125,"nameId":798345,"descriptionId":979889,"spellLevels":[41395,41396,41397]},{"id":13203,"icon":3829,"nameId":816660,"descriptionId":798309,"spellLevels":[41481,45193]},{"id":13175,"icon":128,"nameId":798323,"descriptionId":904106,"spellLevels":[41404,41405,41406]},{"id":13204,"icon":3812,"nameId":798325,"descriptionId":982154,"spellLevels":[41478,44080]},{"id":13173,"icon":126,"nameId":798319,"descriptionId":979870,"spellLevels":[41398,41399,41400]},{"id":13205,"icon":3811,"nameId":798329,"descriptionId":979863,"spellLevels":[41482,44081]},{"id":14511,"icon":4064,"nameId":805351,"descriptionId":979785,"spellLevels":[44213,44214,44215]},{"id":13210,"icon":3828,"nameId":798212,"descriptionId":979925,"spellLevels":[41487]},{"id":13180,"icon":133,"nameId":798336,"descriptionId":979790,"spellLevels":[41419,41420,41421]},{"id":13207,"icon":3824,"nameId":798222,"descriptionId":979921,"spellLevels":[41484,44084]},{"id":13177,"icon":130,"nameId":798233,"descriptionId":979789,"spellLevels":[41410,41411,41412]},{"id":13208,"icon":3827,"nameId":798241,"descriptionId":979820,"spellLevels":[41485]},{"id":13181,"icon":134,"nameId":798322,"descriptionId":979888,"spellLevels":[41422,41423,41424]},{"id":13209,"icon":3823,"nameId":798238,"descriptionId":979819,"spellLevels":[41486]},{"id":13174,"icon":127,"nameId":798312,"descriptionId":979786,"spellLevels":[41401,41402,41403]},{"id":14446,"icon":4063,"nameId":805292,"descriptionId":979809,"spellLevels":[44085]},{"id":13185,"icon":138,"nameId":798219,"descriptionId":979779,"spellLevels":[41434,41435]},{"id":13216,"icon":3819,"nameId":798240,"descriptionId":979797,"spellLevels":[41493]},{"id":13170,"icon":123,"nameId":798246,"descriptionId":798327,"spellLevels":[41389,41390,41391]},{"id":13206,"icon":3830,"nameId":798284,"descriptionId":979893,"spellLevels":[41483]},{"id":13183,"icon":136,"nameId":798247,"descriptionId":983092,"spellLevels":[41428,41429,41430]},{"id":13212,"icon":3821,"nameId":798300,"descriptionId":979804,"spellLevels":[41489]},{"id":13182,"icon":135,"nameId":798271,"descriptionId":979781,"spellLevels":[41425,41426,41427]},{"id":13213,"icon":3822,"nameId":798268,"descriptionId":979924,"spellLevels":[41490]},{"id":13179,"icon":10754,"nameId":798282,"descriptionId":979891,"spellLevels":[41416,41417,41418]},{"id":13214,"icon":3825,"nameId":798245,"descriptionId":979801,"spellLevels":[41491]},{"id":13168,"icon":121,"nameId":798339,"descriptionId":904116,"spellLevels":[41383,41384,41385]},{"id":13215,"icon":3831,"nameId":798292,"descriptionId":979890,"spellLevels":[41492]},{"id":13178,"icon":131,"nameId":798347,"descriptionId":979770,"spellLevels":[41413,41414]},{"id":13211,"icon":3826,"nameId":798308,"descriptionId":979796,"spellLevels":[41488]},{"id":13184,"icon":137,"nameId":798269,"descriptionId":979887,"spellLevels":[41431,41432]},{"id":13217,"icon":3820,"nameId":798297,"descriptionId":979794,"spellLevels":[41494]},{"id":13186,"icon":139,"nameId":798306,"descriptionId":979885,"spellLevels":[41437,41438]},{"id":13218,"icon":3818,"nameId":798265,"descriptionId":979869,"spellLevels":[41495]},{"id":13189,"icon":427,"nameId":816659,"descriptionId":798273,"spellLevels":[41448,45191,45192]},{"id":13220,"icon":3816,"nameId":798220,"descriptionId":979922,"spellLevels":[41497,44083]},{"id":13187,"icon":140,"nameId":798342,"descriptionId":979769,"spellLevels":[41440,41441]},{"id":13219,"icon":3817,"nameId":798264,"descriptionId":979852,"spellLevels":[41496]}],[{"id":13126,"icon":410,"nameId":798161,"descriptionId":932838,"spellLevels":[41334,41335,41336]},{"id":13135,"icon":3727,"nameId":798092,"descriptionId":926287,"spellLevels":[41345,44579]},{"id":13108,"icon":4152,"nameId":798151,"descriptionId":926240,"spellLevels":[41280,41281,41282]},{"id":13148,"icon":3733,"nameId":798197,"descriptionId":932842,"spellLevels":[41358,44576]},{"id":13107,"icon":142,"nameId":798119,"descriptionId":926238,"spellLevels":[41277,41278,41279]},{"id":13143,"icon":3743,"nameId":798154,"descriptionId":933278,"spellLevels":[41353,56403]},{"id":14676,"icon":4065,"nameId":805944,"descriptionId":966359,"spellLevels":[44570,44582,44899]},{"id":13130,"icon":3730,"nameId":798135,"descriptionId":932845,"spellLevels":[41340]},{"id":13110,"icon":145,"nameId":798201,"descriptionId":903321,"spellLevels":[41286,41287,41288]},{"id":13115,"icon":150,"nameId":806043,"descriptionId":926288,"spellLevels":[41301,41302]},{"id":13119,"icon":154,"nameId":798081,"descriptionId":932841,"spellLevels":[41313,41314,41315]},{"id":13138,"icon":3736,"nameId":798210,"descriptionId":926292,"spellLevels":[41348,44897]},{"id":13136,"icon":3745,"nameId":798113,"descriptionId":966641,"spellLevels":[41346,44580,56404]},{"id":13142,"icon":3739,"nameId":798142,"descriptionId":966362,"spellLevels":[41352,56405]},{"id":13116,"icon":151,"nameId":798122,"descriptionId":926419,"spellLevels":[41304,41305,41306]},{"id":13137,"icon":3741,"nameId":798133,"descriptionId":940826,"spellLevels":[41347,44581]},{"id":13123,"icon":158,"nameId":798134,"descriptionId":933259,"spellLevels":[41325,41326,41327]},{"id":13117,"icon":4151,"nameId":798209,"descriptionId":966644,"spellLevels":[41307]},{"id":13124,"icon":159,"nameId":798108,"descriptionId":903205,"spellLevels":[41328,41330]},{"id":13156,"icon":3735,"nameId":798153,"descriptionId":926394,"spellLevels":[41366]},{"id":13113,"icon":148,"nameId":798086,"descriptionId":978893,"spellLevels":[41295,41296,41297]},{"id":13140,"icon":3744,"nameId":926318,"descriptionId":978892,"spellLevels":[41350]},{"id":13109,"icon":144,"nameId":798175,"descriptionId":947709,"spellLevels":[41283,41284,41285]},{"id":13141,"icon":3747,"nameId":798147,"descriptionId":947710,"spellLevels":[41351]},{"id":13118,"icon":153,"nameId":798150,"descriptionId":926273,"spellLevels":[41310,41311,41312]},{"id":14677,"icon":4066,"nameId":805949,"descriptionId":931441,"spellLevels":[44571]},{"id":14818,"icon":4150,"nameId":809157,"descriptionId":932863,"spellLevels":[44902,44903,44904]},{"id":13133,"icon":3729,"nameId":798164,"descriptionId":966360,"spellLevels":[41343]},{"id":13121,"icon":156,"nameId":798187,"descriptionId":926412,"spellLevels":[41319,44900,44901]},{"id":13144,"icon":3738,"nameId":798166,"descriptionId":975775,"spellLevels":[41354]},{"id":13122,"icon":157,"nameId":798200,"descriptionId":926272,"spellLevels":[41322,41323,41324]},{"id":13145,"icon":3737,"nameId":798208,"descriptionId":936461,"spellLevels":[41355]},{"id":13120,"icon":155,"nameId":798183,"descriptionId":926485,"spellLevels":[41316,41318]},{"id":13112,"icon":147,"nameId":798107,"descriptionId":948608,"spellLevels":[41292]},{"id":13125,"icon":160,"nameId":798111,"descriptionId":926276,"spellLevels":[41331,41333]},{"id":13146,"icon":3734,"nameId":798099,"descriptionId":926794,"spellLevels":[41356]},{"id":13111,"icon":146,"nameId":809165,"descriptionId":903244,"spellLevels":[41289,41291]},{"id":13131,"icon":3732,"nameId":798132,"descriptionId":926330,"spellLevels":[41341]},{"id":13106,"icon":141,"nameId":798085,"descriptionId":931437,"spellLevels":[41274,41275,41276]},{"id":13139,"icon":3742,"nameId":798194,"descriptionId":931449,"spellLevels":[41349,44896]},{"id":13134,"icon":3728,"nameId":798087,"descriptionId":966357,"spellLevels":[41344,44578]},{"id":13147,"icon":3746,"nameId":798182,"descriptionId":978898,"spellLevels":[41357]},{"id":13114,"icon":149,"nameId":798207,"descriptionId":933261,"spellLevels":[41298,41299,41300]},{"id":13132,"icon":10376,"nameId":798145,"descriptionId":970418,"spellLevels":[41342]}],[{"id":13055,"icon":169,"nameId":798041,"descriptionId":894307,"spellLevels":[41191,41192,41193]},{"id":13069,"icon":3877,"nameId":798019,"descriptionId":931446,"spellLevels":[41231,44460]},{"id":13047,"icon":161,"nameId":798048,"descriptionId":925346,"spellLevels":[41167,41168,41169]},{"id":13068,"icon":3878,"nameId":798038,"descriptionId":925347,"spellLevels":[41230,44459]},{"id":13050,"icon":174,"nameId":797997,"descriptionId":931447,"spellLevels":[41176,41177]},{"id":13070,"icon":3886,"nameId":797973,"descriptionId":925392,"spellLevels":[41232]},{"id":13051,"icon":165,"nameId":798075,"descriptionId":925350,"spellLevels":[41179,41180,41181]},{"id":13072,"icon":3875,"nameId":797988,"descriptionId":925351,"spellLevels":[41234,44463]},{"id":13058,"icon":172,"nameId":798040,"descriptionId":958862,"spellLevels":[41200,41201,41202]},{"id":13073,"icon":3874,"nameId":798080,"descriptionId":925357,"spellLevels":[41235,44464]},{"id":13053,"icon":167,"nameId":798011,"descriptionId":925365,"spellLevels":[41185,41186,41187]},{"id":13074,"icon":3891,"nameId":798005,"descriptionId":925370,"spellLevels":[41236,44465]},{"id":13054,"icon":168,"nameId":797982,"descriptionId":962994,"spellLevels":[41188,41189,41190]},{"id":13075,"icon":3890,"nameId":798006,"descriptionId":925373,"spellLevels":[41237,44466]},{"id":13066,"icon":180,"nameId":797957,"descriptionId":932766,"spellLevels":[41224,41225,60011]},{"id":13076,"icon":3894,"nameId":797972,"descriptionId":925466,"spellLevels":[41238]},{"id":13056,"icon":170,"nameId":798067,"descriptionId":925376,"spellLevels":[41194,41195,41196]},{"id":13077,"icon":3889,"nameId":798004,"descriptionId":925380,"spellLevels":[41239]},{"id":13057,"icon":171,"nameId":798022,"descriptionId":925381,"spellLevels":[41197,41198,41199]},{"id":13078,"icon":3888,"nameId":798014,"descriptionId":939889,"spellLevels":[41240]},{"id":13052,"icon":166,"nameId":798062,"descriptionId":958837,"spellLevels":[41182,41183,41184]},{"id":13079,"icon":3892,"nameId":797966,"descriptionId":925383,"spellLevels":[41241]},{"id":13059,"icon":173,"nameId":798020,"descriptionId":925384,"spellLevels":[41203,41204,41205]},{"id":13080,"icon":3887,"nameId":798033,"descriptionId":797976,"spellLevels":[41242]},{"id":13062,"icon":176,"nameId":797962,"descriptionId":925388,"spellLevels":[41212,41213,41214]},{"id":13082,"icon":3884,"nameId":798037,"descriptionId":969877,"spellLevels":[41244]},{"id":13061,"icon":175,"nameId":798058,"descriptionId":925390,"spellLevels":[41209,41210,41211]},{"id":13083,"icon":3885,"nameId":836886,"descriptionId":938958,"spellLevels":[41245]},{"id":13064,"icon":178,"nameId":798017,"descriptionId":797990,"spellLevels":[41218,41219,41220]},{"id":13084,"icon":3882,"nameId":797984,"descriptionId":894319,"spellLevels":[41246]},{"id":13049,"icon":163,"nameId":798008,"descriptionId":961440,"spellLevels":[41173,41174,41175]},{"id":13071,"icon":3876,"nameId":798063,"descriptionId":924226,"spellLevels":[41233,44462]},{"id":13063,"icon":177,"nameId":798015,"descriptionId":956832,"spellLevels":[41215,41216]},{"id":13085,"icon":3883,"nameId":806052,"descriptionId":978899,"spellLevels":[41247]},{"id":13065,"icon":179,"nameId":797965,"descriptionId":797969,"spellLevels":[41221,41222]},{"id":13086,"icon":3881,"nameId":798034,"descriptionId":966639,"spellLevels":[41248]},{"id":13067,"icon":418,"nameId":922160,"descriptionId":925348,"spellLevels":[41227,41228,41229]},{"id":13088,"icon":3879,"nameId":798002,"descriptionId":978891,"spellLevels":[41250,44461]},{"id":23510,"icon":10908,"nameId":956892,"descriptionId":961292,"spellLevels":[60027,60028]},{"id":13087,"icon":3880,"nameId":797991,"descriptionId":925398,"spellLevels":[41249]},{"id":23499,"icon":10907,"nameId":956839,"descriptionId":966638,"spellLevels":[60012,60013]},{"id":23508,"icon":10906,"nameId":956866,"descriptionId":978896,"spellLevels":[60022]},{"id":13060,"icon":164,"nameId":797960,"descriptionId":925385,"spellLevels":[41206,41207,41208]},{"id":14636,"icon":4067,"nameId":805605,"descriptionId":958867,"spellLevels":[44469]}],[{"id":13564,"icon":182,"nameId":799061,"descriptionId":972146,"spellLevels":[42223,42269,42270]},{"id":13515,"icon":3585,"nameId":798989,"descriptionId":972147,"spellLevels":[42083,43961]},{"id":13519,"icon":186,"nameId":799095,"descriptionId":972082,"spellLevels":[42093,42094,42095]},{"id":13560,"icon":3581,"nameId":799034,"descriptionId":974564,"spellLevels":[42219,43957]},{"id":13516,"icon":183,"nameId":799069,"descriptionId":967710,"spellLevels":[42084,42085,42086]},{"id":13559,"icon":3580,"nameId":799074,"descriptionId":953962,"spellLevels":[42218,43958]},{"id":14393,"icon":4057,"nameId":804759,"descriptionId":983096,"spellLevels":[43962,43963,43964]},{"id":14396,"icon":4058,"nameId":804763,"descriptionId":983097,"spellLevels":[43974,43975]},{"id":13561,"icon":193,"nameId":799057,"descriptionId":972028,"spellLevels":[42220,42271,42272]},{"id":13526,"icon":3582,"nameId":798949,"descriptionId":972032,"spellLevels":[42108,43979]},{"id":13528,"icon":195,"nameId":799093,"descriptionId":940023,"spellLevels":[42112,42113,42114]},{"id":13563,"icon":3584,"nameId":799044,"descriptionId":940024,"spellLevels":[42222,43999]},{"id":13533,"icon":200,"nameId":799042,"descriptionId":972101,"spellLevels":[42127,42128,57005]},{"id":13562,"icon":3583,"nameId":799037,"descriptionId":972020,"spellLevels":[42221,44000]},{"id":13525,"icon":192,"nameId":799014,"descriptionId":939242,"spellLevels":[42105,42106,42107]},{"id":13565,"icon":3586,"nameId":799023,"descriptionId":972026,"spellLevels":[42224,44002]},{"id":13530,"icon":197,"nameId":799043,"descriptionId":974139,"spellLevels":[42118,42119,42120]},{"id":13566,"icon":3587,"nameId":798956,"descriptionId":978583,"spellLevels":[42225]},{"id":13567,"icon":189,"nameId":798964,"descriptionId":975778,"spellLevels":[42226,42273,42274]},{"id":13522,"icon":3588,"nameId":799090,"descriptionId":975779,"spellLevels":[42100]},{"id":13514,"icon":181,"nameId":799102,"descriptionId":966662,"spellLevels":[42080,42081,42082]},{"id":13568,"icon":3589,"nameId":799112,"descriptionId":966661,"spellLevels":[42227]},{"id":13532,"icon":199,"nameId":905176,"descriptionId":982898,"spellLevels":[42124,42125,42126]},{"id":13569,"icon":3590,"nameId":799020,"descriptionId":982897,"spellLevels":[42228]},{"id":13524,"icon":191,"nameId":799079,"descriptionId":922481,"spellLevels":[42102,42103,42104]},{"id":13570,"icon":3591,"nameId":798975,"descriptionId":929573,"spellLevels":[42229]},{"id":13531,"icon":198,"nameId":799025,"descriptionId":975523,"spellLevels":[42121,42122,42123]},{"id":13571,"icon":3592,"nameId":798981,"descriptionId":905188,"spellLevels":[42230]},{"id":13529,"icon":196,"nameId":798992,"descriptionId":966708,"spellLevels":[42115,42116,42117]},{"id":13572,"icon":3593,"nameId":905178,"descriptionId":966710,"spellLevels":[42231]},{"id":13573,"icon":190,"nameId":799024,"descriptionId":924637,"spellLevels":[42232,42267,42268]},{"id":13523,"icon":3594,"nameId":798945,"descriptionId":972029,"spellLevels":[42101]},{"id":13527,"icon":194,"nameId":799088,"descriptionId":929581,"spellLevels":[42109,42110,42111]},{"id":13574,"icon":3595,"nameId":798947,"descriptionId":982901,"spellLevels":[42233]},{"id":13534,"icon":426,"nameId":905177,"descriptionId":930156,"spellLevels":[42130,42131]},{"id":13579,"icon":3600,"nameId":799030,"descriptionId":966709,"spellLevels":[42238]},{"id":13517,"icon":184,"nameId":798980,"descriptionId":799065,"spellLevels":[42087,42088]},{"id":13576,"icon":3597,"nameId":799031,"descriptionId":964799,"spellLevels":[42235]},{"id":13521,"icon":188,"nameId":798935,"descriptionId":924658,"spellLevels":[42097,42098]},{"id":13577,"icon":3598,"nameId":799070,"descriptionId":929644,"spellLevels":[42236]},{"id":13518,"icon":185,"nameId":799049,"descriptionId":931825,"spellLevels":[42090,42091]},{"id":13575,"icon":3596,"nameId":799067,"descriptionId":975777,"spellLevels":[42234]},{"id":13578,"icon":187,"nameId":798941,"descriptionId":937313,"spellLevels":[42237,42265]},{"id":13520,"icon":3599,"nameId":798953,"descriptionId":972030,"spellLevels":[42096]}],[{"id":12737,"icon":3921,"nameId":797325,"descriptionId":966244,"spellLevels":[40577,43413,43414]},{"id":12760,"icon":4092,"nameId":797343,"descriptionId":966243,"spellLevels":[40614,43415]},{"id":12744,"icon":448,"nameId":835737,"descriptionId":931393,"spellLevels":[40596,40597,40598]},{"id":12765,"icon":3947,"nameId":877512,"descriptionId":928926,"spellLevels":[40619,43416]},{"id":12746,"icon":3958,"nameId":797391,"descriptionId":928939,"spellLevels":[40600,43417,43418]},{"id":12724,"icon":3526,"nameId":797291,"descriptionId":928940,"spellLevels":[40536,40537]},{"id":12733,"icon":436,"nameId":797259,"descriptionId":928941,"spellLevels":[40565,40566,40567]},{"id":12749,"icon":3939,"nameId":797376,"descriptionId":909779,"spellLevels":[40603]},{"id":12736,"icon":438,"nameId":797268,"descriptionId":930857,"spellLevels":[40574,40575,40576]},{"id":12763,"icon":3946,"nameId":797347,"descriptionId":929063,"spellLevels":[40617]},{"id":12745,"icon":3950,"nameId":797251,"descriptionId":928942,"spellLevels":[40599,43419,43420]},{"id":12729,"icon":4084,"nameId":797270,"descriptionId":928985,"spellLevels":[40553]},{"id":12756,"icon":3494,"nameId":797330,"descriptionId":928986,"spellLevels":[40610,43421,43422]},{"id":12726,"icon":3521,"nameId":797281,"descriptionId":928987,"spellLevels":[40544]},{"id":12761,"icon":4085,"nameId":800507,"descriptionId":966467,"spellLevels":[40615,43423,43424]},{"id":14011,"icon":4090,"nameId":800579,"descriptionId":966466,"spellLevels":[43092]},{"id":12738,"icon":435,"nameId":835797,"descriptionId":924700,"spellLevels":[40580,40581,40582]},{"id":12754,"icon":3941,"nameId":797258,"descriptionId":966464,"spellLevels":[40608]},{"id":12734,"icon":442,"nameId":797297,"descriptionId":929048,"spellLevels":[40568,40569,40570]},{"id":12750,"icon":4087,"nameId":797339,"descriptionId":929295,"spellLevels":[40604]},{"id":12731,"icon":432,"nameId":797289,"descriptionId":969170,"spellLevels":[40559,40563,40564]},{"id":12751,"icon":3954,"nameId":797313,"descriptionId":929052,"spellLevels":[40605]},{"id":12739,"icon":440,"nameId":797253,"descriptionId":929053,"spellLevels":[40583,40584,40585]},{"id":12764,"icon":3952,"nameId":797279,"descriptionId":936108,"spellLevels":[40618]},{"id":12723,"icon":447,"nameId":797367,"descriptionId":929054,"spellLevels":[40535,40539]},{"id":12752,"icon":3940,"nameId":797257,"descriptionId":929055,"spellLevels":[40606]},{"id":12728,"icon":4088,"nameId":797309,"descriptionId":929056,"spellLevels":[40550,40551]},{"id":12757,"icon":439,"nameId":797288,"descriptionId":929057,"spellLevels":[40611]},{"id":12759,"icon":449,"nameId":835799,"descriptionId":929060,"spellLevels":[40613,43425]},{"id":12762,"icon":3522,"nameId":797384,"descriptionId":929064,"spellLevels":[40616]},{"id":12743,"icon":3518,"nameId":797276,"descriptionId":922150,"spellLevels":[40593,48089]},{"id":14000,"icon":4086,"nameId":800527,"descriptionId":806571,"spellLevels":[43066]},{"id":12727,"icon":3924,"nameId":797245,"descriptionId":928914,"spellLevels":[40547,40548,40549]},{"id":12755,"icon":3524,"nameId":797252,"descriptionId":928910,"spellLevels":[40609,43410]},{"id":12732,"icon":3523,"nameId":797267,"descriptionId":928917,"spellLevels":[40560,40561,40562]},{"id":12725,"icon":3519,"nameId":797302,"descriptionId":928913,"spellLevels":[40541,40542]},{"id":12730,"icon":3520,"nameId":806566,"descriptionId":928915,"spellLevels":[40556,40557,40558]},{"id":12747,"icon":3945,"nameId":800493,"descriptionId":928916,"spellLevels":[40601,43412]},{"id":12735,"icon":434,"nameId":797307,"descriptionId":931455,"spellLevels":[40571,40572,40573]},{"id":12758,"icon":3942,"nameId":797296,"descriptionId":966843,"spellLevels":[40612,43411]},{"id":12741,"icon":446,"nameId":797294,"descriptionId":929066,"spellLevels":[40589,43650]},{"id":12740,"icon":4091,"nameId":800664,"descriptionId":929089,"spellLevels":[43127]},{"id":12748,"icon":4083,"nameId":800880,"descriptionId":928906,"spellLevels":[40602,43407,43408]},{"id":12753,"icon":3938,"nameId":797353,"descriptionId":928907,"spellLevels":[40607,43409]}],[{"id":12781,"icon":687,"nameId":966953,"descriptionId":977127,"spellLevels":[40644,61177,61178]},{"id":12815,"icon":3651,"nameId":797412,"descriptionId":977136,"spellLevels":[40720,61176]},{"id":12803,"icon":692,"nameId":797522,"descriptionId":977128,"spellLevels":[40708,43746,61175]},{"id":12805,"icon":10930,"nameId":967019,"descriptionId":968219,"spellLevels":[40710,61594]},{"id":12804,"icon":3662,"nameId":797446,"descriptionId":977135,"spellLevels":[40709,43741,43742]},{"id":12780,"icon":686,"nameId":797420,"descriptionId":977134,"spellLevels":[40643,43743]},{"id":12783,"icon":689,"nameId":797495,"descriptionId":977132,"spellLevels":[40650,40651,40652]},{"id":12806,"icon":3659,"nameId":797431,"descriptionId":968130,"spellLevels":[40711,43747]},{"id":12782,"icon":688,"nameId":797515,"descriptionId":977130,"spellLevels":[40647,40648,40649]},{"id":12786,"icon":3656,"nameId":797491,"descriptionId":977137,"spellLevels":[40659,40660]},{"id":12787,"icon":693,"nameId":797417,"descriptionId":971333,"spellLevels":[40662,40737,40738]},{"id":12810,"icon":3652,"nameId":797419,"descriptionId":971334,"spellLevels":[40715,43757]},{"id":12794,"icon":700,"nameId":797427,"descriptionId":971385,"spellLevels":[40681,40682]},{"id":14309,"icon":4042,"nameId":802749,"descriptionId":968132,"spellLevels":[43769]},{"id":12790,"icon":696,"nameId":797518,"descriptionId":977133,"spellLevels":[40669,40670,61602]},{"id":12814,"icon":3653,"nameId":797454,"descriptionId":977143,"spellLevels":[40719]},{"id":12777,"icon":423,"nameId":797447,"descriptionId":975770,"spellLevels":[40634,40635,40636]},{"id":12826,"icon":3663,"nameId":968275,"descriptionId":975771,"spellLevels":[40731]},{"id":12789,"icon":695,"nameId":805018,"descriptionId":971330,"spellLevels":[40666,40667,40668]},{"id":12813,"icon":3654,"nameId":797504,"descriptionId":971393,"spellLevels":[40718]},{"id":12799,"icon":705,"nameId":797516,"descriptionId":975743,"spellLevels":[40696,40697]},{"id":12824,"icon":3643,"nameId":797424,"descriptionId":972386,"spellLevels":[40729]},{"id":12791,"icon":697,"nameId":797520,"descriptionId":977131,"spellLevels":[40672,40673,40674]},{"id":12807,"icon":3658,"nameId":797485,"descriptionId":977138,"spellLevels":[40712,43749]},{"id":12808,"icon":10926,"nameId":797450,"descriptionId":968416,"spellLevels":[40713,61187,61188]},{"id":12821,"icon":3645,"nameId":797488,"descriptionId":977142,"spellLevels":[40726]},{"id":12792,"icon":698,"nameId":797394,"descriptionId":968214,"spellLevels":[40675,40676,40677]},{"id":12816,"icon":3650,"nameId":797486,"descriptionId":968121,"spellLevels":[40721]},{"id":12785,"icon":10929,"nameId":797403,"descriptionId":968459,"spellLevels":[40656,40657,40658]},{"id":12819,"icon":3647,"nameId":797429,"descriptionId":968222,"spellLevels":[40724]},{"id":12788,"icon":10923,"nameId":968085,"descriptionId":968081,"spellLevels":[40663,40664,61186]},{"id":12820,"icon":3646,"nameId":797506,"descriptionId":977141,"spellLevels":[40725]},{"id":12823,"icon":10927,"nameId":797401,"descriptionId":975773,"spellLevels":[40728,61180,61181]},{"id":14307,"icon":4041,"nameId":802625,"descriptionId":977139,"spellLevels":[43750,43751]},{"id":12793,"icon":10924,"nameId":968086,"descriptionId":968084,"spellLevels":[40678,40679,40680]},{"id":12809,"icon":3660,"nameId":797435,"descriptionId":977140,"spellLevels":[40714]},{"id":12784,"icon":690,"nameId":797444,"descriptionId":968212,"spellLevels":[40653,40654]},{"id":12811,"icon":10925,"nameId":797502,"descriptionId":979295,"spellLevels":[40716]},{"id":24038,"icon":699,"nameId":967008,"descriptionId":968077,"spellLevels":[61193,61194]},{"id":12817,"icon":3657,"nameId":797409,"descriptionId":972400,"spellLevels":[40722]},{"id":12796,"icon":702,"nameId":797482,"descriptionId":968397,"spellLevels":[40687,40688,61200]},{"id":12797,"icon":703,"nameId":797396,"descriptionId":968398,"spellLevels":[40690]},{"id":12798,"icon":704,"nameId":797428,"descriptionId":968204,"spellLevels":[40693,61605]},{"id":24039,"icon":10931,"nameId":967033,"descriptionId":977144,"spellLevels":[61196]}],[{"id":13432,"icon":2778,"nameId":798833,"descriptionId":973655,"spellLevels":[41886,41887,41888]},{"id":13470,"icon":3913,"nameId":798760,"descriptionId":973656,"spellLevels":[42006,44020]},{"id":13444,"icon":2808,"nameId":798922,"descriptionId":966684,"spellLevels":[41922,41923,41924]},{"id":13471,"icon":3912,"nameId":922006,"descriptionId":966679,"spellLevels":[42007,44022]},{"id":13435,"icon":2796,"nameId":798867,"descriptionId":966685,"spellLevels":[41895,41896,41897]},{"id":13474,"icon":3897,"nameId":922003,"descriptionId":966680,"spellLevels":[42010,44025]},{"id":13434,"icon":2795,"nameId":798854,"descriptionId":966366,"spellLevels":[41892,41893,41894]},{"id":13472,"icon":3899,"nameId":798894,"descriptionId":966364,"spellLevels":[42008,44023]},{"id":13433,"icon":2794,"nameId":798890,"descriptionId":909842,"spellLevels":[41889,41890,41891]},{"id":13475,"icon":3896,"nameId":798767,"descriptionId":959554,"spellLevels":[42011]},{"id":13437,"icon":2801,"nameId":798781,"descriptionId":915028,"spellLevels":[41901,41902,41903]},{"id":13480,"icon":3909,"nameId":798801,"descriptionId":915032,"spellLevels":[42016,44027]},{"id":13440,"icon":2804,"nameId":798771,"descriptionId":912865,"spellLevels":[41910,41911,54373]},{"id":13469,"icon":3914,"nameId":798929,"descriptionId":961557,"spellLevels":[42005,44021]},{"id":13439,"icon":2803,"nameId":798827,"descriptionId":927263,"spellLevels":[41907,41908,41909]},{"id":13487,"icon":3904,"nameId":798773,"descriptionId":960677,"spellLevels":[42026,55234]},{"id":13436,"icon":2797,"nameId":798886,"descriptionId":966682,"spellLevels":[41898,41899,41900]},{"id":13478,"icon":3911,"nameId":921995,"descriptionId":966686,"spellLevels":[42014]},{"id":13429,"icon":430,"nameId":798840,"descriptionId":910132,"spellLevels":[41879,41941,41942]},{"id":13490,"icon":3901,"nameId":798797,"descriptionId":914978,"spellLevels":[42029]},{"id":14415,"icon":4050,"nameId":805009,"descriptionId":909844,"spellLevels":[44013,44019,54194]},{"id":13483,"icon":3907,"nameId":798917,"descriptionId":916207,"spellLevels":[42022]},{"id":13477,"icon":3900,"nameId":798885,"descriptionId":909845,"spellLevels":[42013,54196,54197]},{"id":13488,"icon":3903,"nameId":798901,"descriptionId":982900,"spellLevels":[42027]},{"id":13431,"icon":2763,"nameId":798924,"descriptionId":966365,"spellLevels":[41883,41884,41885]},{"id":13476,"icon":3895,"nameId":798871,"descriptionId":966363,"spellLevels":[42012]},{"id":13442,"icon":2806,"nameId":798829,"descriptionId":909856,"spellLevels":[41916,41917,41918]},{"id":14414,"icon":4049,"nameId":805007,"descriptionId":959553,"spellLevels":[44012,60030]},{"id":13445,"icon":2809,"nameId":798778,"descriptionId":978936,"spellLevels":[41925,41926,41927]},{"id":14412,"icon":4047,"nameId":804994,"descriptionId":982801,"spellLevels":[44010]},{"id":13438,"icon":2802,"nameId":798772,"descriptionId":931451,"spellLevels":[41904,41905,41906]},{"id":13449,"icon":2813,"nameId":798919,"descriptionId":931452,"spellLevels":[41935]},{"id":13441,"icon":2805,"nameId":798864,"descriptionId":959541,"spellLevels":[41913,41914]},{"id":13479,"icon":10189,"nameId":805059,"descriptionId":982800,"spellLevels":[42015]},{"id":13450,"icon":2815,"nameId":798920,"descriptionId":982798,"spellLevels":[41938,41940]},{"id":13489,"icon":3902,"nameId":798776,"descriptionId":982799,"spellLevels":[42028]},{"id":13446,"icon":2810,"nameId":798798,"descriptionId":917801,"spellLevels":[41928,41929]},{"id":13484,"icon":3906,"nameId":798912,"descriptionId":982887,"spellLevels":[42023]},{"id":13473,"icon":3898,"nameId":798787,"descriptionId":959610,"spellLevels":[42009,60031]},{"id":14411,"icon":4048,"nameId":804992,"descriptionId":909880,"spellLevels":[44007]},{"id":13443,"icon":2807,"nameId":798903,"descriptionId":909882,"spellLevels":[41919,41920]},{"id":13482,"icon":3908,"nameId":798830,"descriptionId":909867,"spellLevels":[42021]},{"id":13491,"icon":2811,"nameId":798824,"descriptionId":966683,"spellLevels":[42030,42032,54193]},{"id":13486,"icon":3905,"nameId":921997,"descriptionId":966681,"spellLevels":[42025]}],[{"id":13405,"icon":2899,"nameId":798756,"descriptionId":964809,"spellLevels":[41816,41835,41836]},{"id":13407,"icon":3560,"nameId":798745,"descriptionId":964810,"spellLevels":[41852,44589]},{"id":13389,"icon":2881,"nameId":798694,"descriptionId":964798,"spellLevels":[41796,41812,41813]},{"id":13420,"icon":3573,"nameId":798674,"descriptionId":967895,"spellLevels":[41865,51207]},{"id":13387,"icon":2879,"nameId":798737,"descriptionId":964803,"spellLevels":[41794,41845,41846]},{"id":13406,"icon":3559,"nameId":798679,"descriptionId":964802,"spellLevels":[41851,44588]},{"id":13386,"icon":2872,"nameId":798702,"descriptionId":964806,"spellLevels":[41793,41847,41848]},{"id":13409,"icon":3562,"nameId":798685,"descriptionId":964807,"spellLevels":[41854,44591]},{"id":13403,"icon":2896,"nameId":798689,"descriptionId":964815,"spellLevels":[41810,41814,41815]},{"id":13410,"icon":3563,"nameId":798703,"descriptionId":964816,"spellLevels":[41855,44592]},{"id":13388,"icon":2880,"nameId":798680,"descriptionId":964804,"spellLevels":[41795,41849,41850]},{"id":13414,"icon":3566,"nameId":798714,"descriptionId":964805,"spellLevels":[41859,51217]},{"id":13394,"icon":2887,"nameId":798749,"descriptionId":964817,"spellLevels":[41801,41841,41842]},{"id":13415,"icon":3567,"nameId":798684,"descriptionId":964820,"spellLevels":[41860,51212]},{"id":13395,"icon":2888,"nameId":798681,"descriptionId":964822,"spellLevels":[41802,41825,41826]},{"id":14682,"icon":4069,"nameId":806032,"descriptionId":964823,"spellLevels":[44586,44587]},{"id":13398,"icon":2891,"nameId":798673,"descriptionId":964825,"spellLevels":[41805,41837,41838]},{"id":13411,"icon":3564,"nameId":798667,"descriptionId":964824,"spellLevels":[44593]},{"id":13400,"icon":2893,"nameId":798754,"descriptionId":964826,"spellLevels":[41807,41817,41818]},{"id":13412,"icon":3579,"nameId":798742,"descriptionId":964827,"spellLevels":[41857]},{"id":13392,"icon":2885,"nameId":798709,"descriptionId":964828,"spellLevels":[41799,41843,41844]},{"id":13393,"icon":2886,"nameId":798712,"descriptionId":964829,"spellLevels":[41800]},{"id":13397,"icon":2890,"nameId":798724,"descriptionId":964831,"spellLevels":[41804,41819,41820]},{"id":13417,"icon":3569,"nameId":798706,"descriptionId":979577,"spellLevels":[41862]},{"id":13402,"icon":2895,"nameId":798665,"descriptionId":966174,"spellLevels":[41809,41821,41822]},{"id":13426,"icon":3570,"nameId":798671,"descriptionId":964835,"spellLevels":[41871]},{"id":13401,"icon":10880,"nameId":798755,"descriptionId":964838,"spellLevels":[41808,41823,41824]},{"id":13418,"icon":3571,"nameId":798741,"descriptionId":964840,"spellLevels":[41863]},{"id":13391,"icon":2883,"nameId":798732,"descriptionId":964841,"spellLevels":[41798,41827,41828]},{"id":13419,"icon":3572,"nameId":798687,"descriptionId":964865,"spellLevels":[41864]},{"id":13408,"icon":3561,"nameId":798697,"descriptionId":964843,"spellLevels":[41853,44590,51218]},{"id":13422,"icon":3574,"nameId":798735,"descriptionId":964844,"spellLevels":[41867]},{"id":13399,"icon":2892,"nameId":798708,"descriptionId":964845,"spellLevels":[41806,41829,41830]},{"id":13404,"icon":2897,"nameId":798699,"descriptionId":964846,"spellLevels":[41811]},{"id":18650,"icon":4291,"nameId":871345,"descriptionId":964864,"spellLevels":[51219,51220]},{"id":18651,"icon":4292,"nameId":871348,"descriptionId":964862,"spellLevels":[51221]},{"id":13396,"icon":2889,"nameId":798664,"descriptionId":964854,"spellLevels":[41803,41834]},{"id":13423,"icon":3575,"nameId":798717,"descriptionId":964852,"spellLevels":[41868]},{"id":13390,"icon":2882,"nameId":798720,"descriptionId":964855,"spellLevels":[41797,41839]},{"id":14681,"icon":4070,"nameId":806030,"descriptionId":964853,"spellLevels":[44585]},{"id":13421,"icon":3577,"nameId":798663,"descriptionId":964849,"spellLevels":[41866,41874]},{"id":13425,"icon":3578,"nameId":798695,"descriptionId":964850,"spellLevels":[41870]},{"id":13424,"icon":3576,"nameId":798746,"descriptionId":964877,"spellLevels":[41869,41876]},{"id":13385,"icon":2849,"nameId":798722,"descriptionId":964872,"spellLevels":[41792]}],[{"id":13823,"icon":3206,"nameId":799512,"descriptionId":964377,"spellLevels":[42728,42758,42759]},{"id":13858,"icon":3617,"nameId":799481,"descriptionId":799525,"spellLevels":[42838,43761]},{"id":13827,"icon":3210,"nameId":799516,"descriptionId":799461,"spellLevels":[42732,42756,42757]},{"id":13857,"icon":3613,"nameId":964387,"descriptionId":799491,"spellLevels":[42837,43762]},{"id":13829,"icon":3212,"nameId":799580,"descriptionId":976329,"spellLevels":[42734,42754,42755]},{"id":13859,"icon":3611,"nameId":799478,"descriptionId":976334,"spellLevels":[42839,43763]},{"id":13832,"icon":3215,"nameId":799518,"descriptionId":970724,"spellLevels":[42737,42760,42761]},{"id":13860,"icon":3608,"nameId":799496,"descriptionId":970725,"spellLevels":[42840,43764]},{"id":13822,"icon":3205,"nameId":799529,"descriptionId":904039,"spellLevels":[42727,42762,42763]},{"id":13861,"icon":3618,"nameId":799583,"descriptionId":964390,"spellLevels":[42841,43765]},{"id":13834,"icon":3217,"nameId":799505,"descriptionId":964564,"spellLevels":[42739,42764,42765]},{"id":13862,"icon":3606,"nameId":799556,"descriptionId":964565,"spellLevels":[42842,43766]},{"id":13819,"icon":3202,"nameId":799500,"descriptionId":964378,"spellLevels":[42724,42766,42767]},{"id":13863,"icon":3621,"nameId":799625,"descriptionId":964399,"spellLevels":[42843,43767]},{"id":13830,"icon":3213,"nameId":799534,"descriptionId":976331,"spellLevels":[42735,42768,42769]},{"id":13864,"icon":3610,"nameId":799561,"descriptionId":976333,"spellLevels":[42844,43768]},{"id":13821,"icon":3204,"nameId":799611,"descriptionId":904038,"spellLevels":[42726,42770,42771]},{"id":13824,"icon":3207,"nameId":799550,"descriptionId":964388,"spellLevels":[42785]},{"id":13820,"icon":3203,"nameId":799558,"descriptionId":903990,"spellLevels":[42725,42772,42773]},{"id":13866,"icon":10190,"nameId":799597,"descriptionId":799539,"spellLevels":[42846]},{"id":13826,"icon":3209,"nameId":799552,"descriptionId":964379,"spellLevels":[42731,42774,42775]},{"id":13867,"icon":3614,"nameId":799527,"descriptionId":904040,"spellLevels":[42847]},{"id":13838,"icon":3221,"nameId":799579,"descriptionId":964394,"spellLevels":[42743,42776,42777]},{"id":13868,"icon":3602,"nameId":799490,"descriptionId":966878,"spellLevels":[42848]},{"id":13831,"icon":3214,"nameId":799506,"descriptionId":976330,"spellLevels":[42736,42778,42779]},{"id":13869,"icon":3609,"nameId":799624,"descriptionId":976332,"spellLevels":[42849]},{"id":13837,"icon":3220,"nameId":799577,"descriptionId":964630,"spellLevels":[42742,42780,42781]},{"id":13870,"icon":3603,"nameId":799466,"descriptionId":964631,"spellLevels":[42850]},{"id":13836,"icon":3219,"nameId":799610,"descriptionId":964626,"spellLevels":[42741,42782,42783]},{"id":13871,"icon":3604,"nameId":799484,"descriptionId":964632,"spellLevels":[42851]},{"id":13865,"icon":3619,"nameId":799547,"descriptionId":904041,"spellLevels":[42845,43759,43760]},{"id":13872,"icon":3616,"nameId":799472,"descriptionId":964619,"spellLevels":[42852]},{"id":13835,"icon":3218,"nameId":799585,"descriptionId":964627,"spellLevels":[42740,42786,42787]},{"id":13873,"icon":3605,"nameId":799623,"descriptionId":964628,"spellLevels":[42853]},{"id":13849,"icon":3277,"nameId":966261,"descriptionId":964640,"spellLevels":[42810,42812]},{"id":13877,"icon":3601,"nameId":799515,"descriptionId":964642,"spellLevels":[42857]},{"id":13825,"icon":3208,"nameId":799502,"descriptionId":904042,"spellLevels":[42730,42789]},{"id":13874,"icon":3615,"nameId":799567,"descriptionId":799571,"spellLevels":[42854]},{"id":13828,"icon":3211,"nameId":799620,"descriptionId":969879,"spellLevels":[42733,42791]},{"id":13875,"icon":3612,"nameId":799618,"descriptionId":904057,"spellLevels":[42855]},{"id":13833,"icon":3216,"nameId":799469,"descriptionId":964636,"spellLevels":[42738,42793]},{"id":14306,"icon":4043,"nameId":802623,"descriptionId":964637,"spellLevels":[43748]},{"id":14308,"icon":4044,"nameId":802627,"descriptionId":964396,"spellLevels":[43753,43754]},{"id":13876,"icon":3607,"nameId":799473,"descriptionId":964650,"spellLevels":[42856]}],[{"id":14574,"icon":3357,"nameId":805486,"descriptionId":964086,"spellLevels":[44339,44340,44341]},{"id":14604,"icon":3837,"nameId":805433,"descriptionId":964085,"spellLevels":[44426,44482]},{"id":14575,"icon":3358,"nameId":805388,"descriptionId":964175,"spellLevels":[44342,44343,44344]},{"id":14602,"icon":3836,"nameId":805480,"descriptionId":964084,"spellLevels":[44424,44483]},{"id":14584,"icon":3359,"nameId":805475,"descriptionId":805462,"spellLevels":[44369,44370,44371]},{"id":14603,"icon":3835,"nameId":805482,"descriptionId":964083,"spellLevels":[44425,44484]},{"id":14583,"icon":3360,"nameId":805378,"descriptionId":964052,"spellLevels":[44366,44367,44368]},{"id":14605,"icon":3834,"nameId":805368,"descriptionId":964082,"spellLevels":[44427,44485]},{"id":14579,"icon":3361,"nameId":805469,"descriptionId":964055,"spellLevels":[44354,44355,44356]},{"id":14606,"icon":3833,"nameId":805377,"descriptionId":964189,"spellLevels":[44428,44486]},{"id":14582,"icon":3362,"nameId":805468,"descriptionId":964056,"spellLevels":[44363,44364,44365]},{"id":14607,"icon":3832,"nameId":805491,"descriptionId":964080,"spellLevels":[44429,44487]},{"id":14588,"icon":3363,"nameId":805492,"descriptionId":805391,"spellLevels":[44381,44382,44383]},{"id":14608,"icon":3852,"nameId":805432,"descriptionId":964275,"spellLevels":[44430,44488]},{"id":14580,"icon":3364,"nameId":805493,"descriptionId":964057,"spellLevels":[44357,44358,44359]},{"id":14609,"icon":3851,"nameId":805431,"descriptionId":964078,"spellLevels":[44431,44489]},{"id":14581,"icon":3365,"nameId":805441,"descriptionId":891260,"spellLevels":[44360,44361,44362]},{"id":14590,"icon":3372,"nameId":805456,"descriptionId":968771,"spellLevels":[44387]},{"id":14577,"icon":3366,"nameId":805438,"descriptionId":964065,"spellLevels":[44348,44349,44350]},{"id":14611,"icon":3849,"nameId":805406,"descriptionId":964074,"spellLevels":[44433]},{"id":14585,"icon":3367,"nameId":805460,"descriptionId":964077,"spellLevels":[44372,44373,44374]},{"id":14612,"icon":3848,"nameId":805453,"descriptionId":976328,"spellLevels":[44434]},{"id":14592,"icon":3368,"nameId":805415,"descriptionId":964062,"spellLevels":[44393,44394,44395]},{"id":14613,"icon":3847,"nameId":805613,"descriptionId":964126,"spellLevels":[44435]},{"id":14587,"icon":3369,"nameId":805408,"descriptionId":964061,"spellLevels":[44378,44379,44380]},{"id":14614,"icon":3846,"nameId":805477,"descriptionId":964125,"spellLevels":[44436]},{"id":14576,"icon":3370,"nameId":964059,"descriptionId":964060,"spellLevels":[44345,44346,44347]},{"id":14637,"icon":4061,"nameId":805607,"descriptionId":964186,"spellLevels":[44470]},{"id":14589,"icon":3371,"nameId":805484,"descriptionId":964058,"spellLevels":[44384,44385,44386]},{"id":14616,"icon":3844,"nameId":805430,"descriptionId":805479,"spellLevels":[44438]},{"id":14615,"icon":3845,"nameId":805427,"descriptionId":964064,"spellLevels":[44437,44478,44479]},{"id":14617,"icon":3843,"nameId":805476,"descriptionId":964121,"spellLevels":[44439]},{"id":14593,"icon":3373,"nameId":805474,"descriptionId":964066,"spellLevels":[44396,44397,44398]},{"id":14618,"icon":3842,"nameId":805417,"descriptionId":964299,"spellLevels":[44440]},{"id":14591,"icon":3377,"nameId":805418,"descriptionId":964067,"spellLevels":[44390,44391]},{"id":14622,"icon":4297,"nameId":805423,"descriptionId":972914,"spellLevels":[44444]},{"id":14610,"icon":3850,"nameId":805367,"descriptionId":964173,"spellLevels":[44432,44480]},{"id":14595,"icon":3375,"nameId":805473,"descriptionId":964177,"spellLevels":[44402]},{"id":14594,"icon":3374,"nameId":805470,"descriptionId":964174,"spellLevels":[44399,44400]},{"id":14619,"icon":3841,"nameId":805463,"descriptionId":964178,"spellLevels":[44441]},{"id":14638,"icon":4062,"nameId":805609,"descriptionId":964172,"spellLevels":[44471,44481]},{"id":14620,"icon":3840,"nameId":805376,"descriptionId":964176,"spellLevels":[44442]},{"id":14596,"icon":3376,"nameId":805424,"descriptionId":964185,"spellLevels":[44405,44406]},{"id":14621,"icon":3839,"nameId":805419,"descriptionId":964102,"spellLevels":[44443]}],[{"id":13668,"icon":3400,"nameId":799140,"descriptionId":978797,"spellLevels":[42412,42469,42470]},{"id":13711,"icon":4052,"nameId":799210,"descriptionId":978812,"spellLevels":[42524,43850]},{"id":13669,"icon":3399,"nameId":799279,"descriptionId":978796,"spellLevels":[42413,42465,42466]},{"id":13709,"icon":3752,"nameId":799276,"descriptionId":978813,"spellLevels":[42522,43847]},{"id":13670,"icon":3388,"nameId":799290,"descriptionId":978795,"spellLevels":[42414,42481,42482]},{"id":13710,"icon":3751,"nameId":799238,"descriptionId":978809,"spellLevels":[42523,43849]},{"id":13666,"icon":3382,"nameId":965061,"descriptionId":978794,"spellLevels":[42410,42471,42472]},{"id":13708,"icon":3750,"nameId":799285,"descriptionId":978808,"spellLevels":[42521,43848]},{"id":13667,"icon":3402,"nameId":799182,"descriptionId":978793,"spellLevels":[42411,42467,42468]},{"id":13712,"icon":3749,"nameId":799286,"descriptionId":978807,"spellLevels":[42525,43851]},{"id":13674,"icon":3386,"nameId":799229,"descriptionId":978792,"spellLevels":[42418,42463,42464]},{"id":13725,"icon":3756,"nameId":799196,"descriptionId":978806,"spellLevels":[42538,43853]},{"id":13679,"icon":3389,"nameId":799219,"descriptionId":978791,"spellLevels":[42423,42457,42458]},{"id":13715,"icon":3762,"nameId":799254,"descriptionId":978805,"spellLevels":[42528,43854]},{"id":13696,"icon":3401,"nameId":799235,"descriptionId":965741,"spellLevels":[42493,42494,42495]},{"id":13716,"icon":3753,"nameId":799178,"descriptionId":969452,"spellLevels":[42529]},{"id":13680,"icon":3395,"nameId":799150,"descriptionId":978790,"spellLevels":[42424,42455,42456]},{"id":13718,"icon":3761,"nameId":799209,"descriptionId":978804,"spellLevels":[42531]},{"id":13676,"icon":3391,"nameId":799255,"descriptionId":978789,"spellLevels":[42420,42459,42460]},{"id":13717,"icon":3757,"nameId":799190,"descriptionId":978803,"spellLevels":[42530]},{"id":13695,"icon":3397,"nameId":799265,"descriptionId":978785,"spellLevels":[42490,42492]},{"id":13719,"icon":3755,"nameId":799227,"descriptionId":965925,"spellLevels":[42532]},{"id":13682,"icon":3387,"nameId":799141,"descriptionId":979235,"spellLevels":[42426,42483,42484]},{"id":13720,"icon":3763,"nameId":799288,"descriptionId":982188,"spellLevels":[42533]},{"id":13681,"icon":3384,"nameId":799283,"descriptionId":978787,"spellLevels":[42425,42453,42454]},{"id":13721,"icon":3766,"nameId":799181,"descriptionId":978802,"spellLevels":[42534]},{"id":13701,"icon":3392,"nameId":799264,"descriptionId":966028,"spellLevels":[42509,42510,42511]},{"id":13727,"icon":3767,"nameId":799189,"descriptionId":965791,"spellLevels":[42540]},{"id":13677,"icon":3394,"nameId":799223,"descriptionId":978786,"spellLevels":[42421,42473,42474]},{"id":13723,"icon":3758,"nameId":799275,"descriptionId":978801,"spellLevels":[42536]},{"id":13684,"icon":3385,"nameId":799261,"descriptionId":965865,"spellLevels":[42428,42479,42480]},{"id":13724,"icon":3765,"nameId":799272,"descriptionId":965866,"spellLevels":[42537]},{"id":13678,"icon":3396,"nameId":799187,"descriptionId":978784,"spellLevels":[42422,42430]},{"id":13714,"icon":3764,"nameId":799155,"descriptionId":978800,"spellLevels":[42527]},{"id":13675,"icon":3393,"nameId":799164,"descriptionId":978783,"spellLevels":[42419,42462]},{"id":13726,"icon":3759,"nameId":799269,"descriptionId":978799,"spellLevels":[42539]},{"id":13697,"icon":3383,"nameId":799287,"descriptionId":965862,"spellLevels":[42496,42498]},{"id":13722,"icon":3760,"nameId":799248,"descriptionId":965916,"spellLevels":[42535]},{"id":13683,"icon":3398,"nameId":799186,"descriptionId":976502,"spellLevels":[42427,42475,42476]},{"id":13728,"icon":3754,"nameId":799304,"descriptionId":976501,"spellLevels":[42541]},{"id":13672,"icon":3390,"nameId":799193,"descriptionId":965082,"spellLevels":[42416,42477,42478]},{"id":13713,"icon":3748,"nameId":799237,"descriptionId":965915,"spellLevels":[42526,43852]},{"id":14341,"icon":4051,"nameId":803621,"descriptionId":965760,"spellLevels":[43844,43846]},{"id":14342,"icon":3768,"nameId":803626,"descriptionId":978798,"spellLevels":[43845]}],[{"id":13770,"icon":3548,"nameId":799373,"descriptionId":965970,"spellLevels":[42640,42641,42642]},{"id":13806,"icon":3668,"nameId":799320,"descriptionId":965973,"spellLevels":[42708,43882]},{"id":13748,"icon":3532,"nameId":799359,"descriptionId":969355,"spellLevels":[42580,42581,42582]},{"id":13786,"icon":3684,"nameId":799452,"descriptionId":969354,"spellLevels":[42688,43869]},{"id":13756,"icon":3538,"nameId":799319,"descriptionId":979227,"spellLevels":[42600,42601,42602]},{"id":13787,"icon":3678,"nameId":799355,"descriptionId":979233,"spellLevels":[42689,43870]},{"id":13760,"icon":3541,"nameId":799421,"descriptionId":965964,"spellLevels":[42610,42611,42612]},{"id":13788,"icon":3675,"nameId":965967,"descriptionId":966405,"spellLevels":[42690,43877]},{"id":13768,"icon":3546,"nameId":799331,"descriptionId":965963,"spellLevels":[42634,42635,42636]},{"id":13789,"icon":3670,"nameId":799344,"descriptionId":965985,"spellLevels":[42691,43878]},{"id":13754,"icon":3536,"nameId":799444,"descriptionId":965962,"spellLevels":[42594,42595,42596]},{"id":13790,"icon":3680,"nameId":799400,"descriptionId":966088,"spellLevels":[42692,43880]},{"id":13769,"icon":3547,"nameId":799407,"descriptionId":966387,"spellLevels":[42637,42638,42639]},{"id":13791,"icon":3669,"nameId":799456,"descriptionId":966398,"spellLevels":[42693]},{"id":13774,"icon":3534,"nameId":799435,"descriptionId":966291,"spellLevels":[42652,42653,42654]},{"id":13792,"icon":3682,"nameId":799420,"descriptionId":979232,"spellLevels":[42694,43889]},{"id":13757,"icon":3539,"nameId":799401,"descriptionId":965979,"spellLevels":[42603,42604,42605]},{"id":13793,"icon":3677,"nameId":799436,"descriptionId":966085,"spellLevels":[42695,43891]},{"id":13763,"icon":3543,"nameId":799341,"descriptionId":966394,"spellLevels":[42619,42620,42621]},{"id":13794,"icon":3673,"nameId":799322,"descriptionId":979231,"spellLevels":[42696]},{"id":13755,"icon":3537,"nameId":799454,"descriptionId":966393,"spellLevels":[42597,42598,42599]},{"id":13795,"icon":3679,"nameId":799332,"descriptionId":965981,"spellLevels":[42697]},{"id":13765,"icon":3544,"nameId":799432,"descriptionId":966392,"spellLevels":[42625,42626,42627]},{"id":13796,"icon":3672,"nameId":799306,"descriptionId":965980,"spellLevels":[42698]},{"id":13771,"icon":3549,"nameId":799440,"descriptionId":966391,"spellLevels":[42643,42644,42645]},{"id":13797,"icon":3667,"nameId":799447,"descriptionId":966402,"spellLevels":[42699]},{"id":13772,"icon":3550,"nameId":966260,"descriptionId":966844,"spellLevels":[42646,42647,42648]},{"id":13798,"icon":3666,"nameId":799339,"descriptionId":966400,"spellLevels":[42700]},{"id":13766,"icon":3545,"nameId":799430,"descriptionId":979226,"spellLevels":[42628,42629,42630]},{"id":13799,"icon":3671,"nameId":799406,"descriptionId":979230,"spellLevels":[42701]},{"id":13762,"icon":3542,"nameId":966052,"descriptionId":965993,"spellLevels":[42616,42617,42618]},{"id":13800,"icon":3674,"nameId":799376,"descriptionId":965995,"spellLevels":[42702]},{"id":13781,"icon":3557,"nameId":799349,"descriptionId":966017,"spellLevels":[42665,42666]},{"id":13801,"icon":3664,"nameId":799379,"descriptionId":966099,"spellLevels":[42703]},{"id":13758,"icon":3540,"nameId":799382,"descriptionId":966013,"spellLevels":[42606,42607,42608]},{"id":13802,"icon":3676,"nameId":799353,"descriptionId":966007,"spellLevels":[42704]},{"id":13773,"icon":3551,"nameId":799428,"descriptionId":966386,"spellLevels":[42649,42650]},{"id":13803,"icon":3665,"nameId":799354,"descriptionId":966009,"spellLevels":[42705]},{"id":13753,"icon":3535,"nameId":799358,"descriptionId":979225,"spellLevels":[42591,42592]},{"id":13804,"icon":3681,"nameId":799330,"descriptionId":979229,"spellLevels":[42706]},{"id":13749,"icon":3533,"nameId":799458,"descriptionId":966384,"spellLevels":[42583,42584]},{"id":13805,"icon":3683,"nameId":799397,"descriptionId":979228,"spellLevels":[42707]},{"id":14321,"icon":4053,"nameId":803306,"descriptionId":966024,"spellLevels":[43816,43900]},{"id":14357,"icon":10610,"nameId":803972,"descriptionId":965999,"spellLevels":[43901]}],[],[{"id":23432,"icon":4313,"nameId":952366,"descriptionId":978531,"spellLevels":[59845,61685,62407]},{"id":23729,"icon":4303,"nameId":971563,"descriptionId":981228,"spellLevels":[60556,61651]},{"id":23719,"icon":4300,"nameId":963045,"descriptionId":978550,"spellLevels":[60542,61645,61646]},{"id":23263,"icon":4343,"nameId":948700,"descriptionId":982615,"spellLevels":[59439,61649]},{"id":23801,"icon":4301,"nameId":964679,"descriptionId":985359,"spellLevels":[60674,61647,61648]},{"id":23828,"icon":4339,"nameId":964403,"descriptionId":978777,"spellLevels":[60723,62477]},{"id":23747,"icon":4325,"nameId":963153,"descriptionId":978674,"spellLevels":[60581,61682,62410]},{"id":23392,"icon":4299,"nameId":952356,"descriptionId":981131,"spellLevels":[59799,61643]},{"id":23734,"icon":4311,"nameId":973701,"descriptionId":978558,"spellLevels":[60561,61683,62412]},{"id":23720,"icon":4314,"nameId":963047,"descriptionId":982614,"spellLevels":[60543,61686]},{"id":23824,"icon":4304,"nameId":964351,"descriptionId":982597,"spellLevels":[60718,61653,61654]},{"id":23401,"icon":4337,"nameId":949885,"descriptionId":978778,"spellLevels":[59809,62496]},{"id":23393,"icon":4321,"nameId":952372,"descriptionId":978565,"spellLevels":[59800,61669,61670]},{"id":23755,"icon":4332,"nameId":963246,"descriptionId":982610,"spellLevels":[60591,62431]},{"id":23736,"icon":4338,"nameId":963111,"descriptionId":978668,"spellLevels":[60565,62413,62414]},{"id":23742,"icon":4333,"nameId":963127,"descriptionId":978780,"spellLevels":[60571,62433]},{"id":23330,"icon":4323,"nameId":949277,"descriptionId":984887,"spellLevels":[59713,61665,61666]},{"id":23841,"icon":4335,"nameId":964651,"descriptionId":981900,"spellLevels":[60743]},{"id":23754,"icon":4302,"nameId":963244,"descriptionId":977088,"spellLevels":[60590,61675,61676]},{"id":23434,"icon":4336,"nameId":952370,"descriptionId":982056,"spellLevels":[59848]},{"id":23741,"icon":4327,"nameId":963125,"descriptionId":978684,"spellLevels":[60570,61677,62422]},{"id":23731,"icon":4322,"nameId":963101,"descriptionId":973299,"spellLevels":[60558]},{"id":23391,"icon":4329,"nameId":952997,"descriptionId":978685,"spellLevels":[59798,61678,62423]},{"id":23743,"icon":4340,"nameId":963129,"descriptionId":984890,"spellLevels":[60572]},{"id":23726,"icon":4330,"nameId":963066,"descriptionId":982077,"spellLevels":[60549,61890,62426]},{"id":23753,"icon":4341,"nameId":963230,"descriptionId":979009,"spellLevels":[60588]},{"id":23823,"icon":4307,"nameId":964348,"descriptionId":978698,"spellLevels":[60717,61659,61660]},{"id":23829,"icon":4318,"nameId":964761,"descriptionId":982567,"spellLevels":[60724]},{"id":23750,"icon":4308,"nameId":963189,"descriptionId":978701,"spellLevels":[60584,63168,63169]},{"id":24219,"icon":4319,"nameId":970634,"descriptionId":979011,"spellLevels":[61562]},{"id":23314,"icon":4324,"nameId":949156,"descriptionId":978704,"spellLevels":[59682,61667,61668]},{"id":23838,"icon":4312,"nameId":964675,"descriptionId":981902,"spellLevels":[60737]},{"id":23735,"icon":4309,"nameId":963109,"descriptionId":984549,"spellLevels":[60564,61851,61852]},{"id":23756,"icon":4310,"nameId":963249,"descriptionId":982371,"spellLevels":[60592]},{"id":23826,"icon":4326,"nameId":964373,"descriptionId":984891,"spellLevels":[60720,61673]},{"id":23319,"icon":4315,"nameId":949192,"descriptionId":985054,"spellLevels":[59689]},{"id":23268,"icon":4305,"nameId":952353,"descriptionId":982360,"spellLevels":[59444,61655]},{"id":23738,"icon":4316,"nameId":963116,"descriptionId":982161,"spellLevels":[60567]},{"id":23386,"icon":4328,"nameId":949776,"descriptionId":983086,"spellLevels":[59789,61681]},{"id":23842,"icon":4334,"nameId":964653,"descriptionId":979029,"spellLevels":[60744]},{"id":23723,"icon":4306,"nameId":963059,"descriptionId":983300,"spellLevels":[60546,61809]},{"id":23396,"icon":4317,"nameId":982644,"descriptionId":979028,"spellLevels":[59803]},{"id":23834,"icon":4331,"nameId":971755,"descriptionId":977344,"spellLevels":[60731,61894]},{"id":23846,"icon":4342,"nameId":964667,"descriptionId":984894,"spellLevels":[60748]}]]